sciop_cli-0.3.0.dist-info/METADATA
sciop_cli-0.3.0.dist-info/WHEEL
sciop_cli-0.3.0.dist-info/entry_points.txt
sciop_cli-0.3.0.dist-info/licenses/LICENSE
sciop_cli/__init__.py
sciop_cli/__main__.py
sciop_cli/api.py
sciop_cli/cli/__init__.py
sciop_cli/cli/api.py
sciop_cli/cli/client.py
sciop_cli/cli/main.py
sciop_cli/cli/manifest.py
sciop_cli/cli/pack.py
sciop_cli/cli/torrent.py
sciop_cli/clients/__init__.py
sciop_cli/clients/base.py
sciop_cli/clients/qbt.py
sciop_cli/config.py
sciop_cli/const.py
sciop_cli/data.py
sciop_cli/exceptions.py
sciop_cli/models/__init__.py
sciop_cli/models/pack.py
sciop_cli/models/sciop.py
sciop_cli/pack.py
sciop_cli/schema.py
sciop_cli/torrent.py
sciop_cli/types.py
sciop_cli-0.3.0.dist-info/RECORD
