Metadata-Version: 2.1
Name: sciop-cli
Version: 0.3.0
Summary: A CLI for sciop
Author-Email: cosmicexplorer <dmcC2@hypnicjerk.ai>, sneakers-the-rat <sneakers-the-rat@protonmail.com>
License: EUPL-1.2
Project-URL: repository, https://codeberg.org/safeguarding/sciop-cli
Project-URL: homepage, https://sciop.net
Requires-Python: >=3.11
Requires-Dist: libtorrent>=2.0.11
Requires-Dist: click>=8.1.8
Requires-Dist: click-option-group>=0.5.6
Requires-Dist: pydantic>=2.10.6
Requires-Dist: bencode-rs>=0.0.7
Requires-Dist: platformdirs>=4.3.8
Requires-Dist: requests>=2.32.3
Requires-Dist: tqdm>=4.67.1
Requires-Dist: rich>=14.0.0
Requires-Dist: humanize>=4.12.2
Requires-Dist: pydantic-settings>=2.9.1
Requires-Dist: keyring>=25.6.0
Requires-Dist: pyyaml>=6.0.2
Requires-Dist: zstandard>=0.22
Requires-Dist: qbittorrent-api>=2025.5.0
Requires-Dist: typing-extensions>=4.10.0; python_version < "3.12"
Provides-Extra: mypy
Requires-Dist: mypy>=1.15; extra == "mypy"
Requires-Dist: types-tqdm>=4.67.0.20250401; extra == "mypy"
Requires-Dist: types-requests>=2.32.0.20250328; extra == "mypy"
Requires-Dist: types-PyYAML>=6.0.12.20250516; extra == "mypy"
Provides-Extra: dev
Requires-Dist: sciop-cli[mypy]; extra == "dev"
Requires-Dist: ruff>=0.9.7; extra == "dev"
Requires-Dist: black>=25.1.0; extra == "dev"
